mrcnn/__init__.py
mrcnn/config.py
mrcnn/model.py
mrcnn/parallel_model.py
mrcnn/utils.py
mrcnn/visualize.py
mrcnn_colab-2.1.dist-info/LICENSE
mrcnn_colab-2.1.dist-info/METADATA
mrcnn_colab-2.1.dist-info/WHEEL
mrcnn_colab-2.1.dist-info/top_level.txt
mrcnn_colab-2.1.dist-info/RECORD
